README.txt
setup.cfg
setup.py
collective/__init__.py
collective.portlet.debuginfo.egg-info/PKG-INFO
collective.portlet.debuginfo.egg-info/SOURCES.txt
collective.portlet.debuginfo.egg-info/dependency_links.txt
collective.portlet.debuginfo.egg-info/entry_points.txt
collective.portlet.debuginfo.egg-info/namespace_packages.txt
collective.portlet.debuginfo.egg-info/not-zip-safe
collective.portlet.debuginfo.egg-info/paster_plugins.txt
collective.portlet.debuginfo.egg-info/requires.txt
collective.portlet.debuginfo.egg-info/top_level.txt
collective/portlet/__init__.py
collective/portlet/debuginfo/__init__.py
collective/portlet/debuginfo/configure.zcml
collective/portlet/debuginfo/debuginfoportlet.pt
collective/portlet/debuginfo/debuginfoportlet.py
collective/portlet/debuginfo/permissions.py
collective/portlet/debuginfo/version.txt
collective/portlet/debuginfo/profiles/default/metadata.xml
collective/portlet/debuginfo/profiles/default/portlets.xml
collective/portlet/debuginfo/tests/__init__.py
collective/portlet/debuginfo/tests/base.py
collective/portlet/debuginfo/tests/test_portlet.py
docs/HISTORY.txt
docs/INSTALL.txt
docs/LICENSE.GPL
docs/LICENSE.txt