Metadata-Version: 1.0
Name: collective.portlet.debuginfo
Version: 1.0
Summary: A helper portlet which displays some usefull info about current user/context.
Home-page: http://dms4u.cz/products
Author: Lukas Zdych
Author-email: lukas.zdych@dms4u.cz
License: GPL
Keywords: plone portlet debug
Platform: UNKNOWN
Classifier: Framework :: Plone
Classifier: Programming Language :: Python
Classifier: Topic :: Software Development :: Libraries :: Python Modules
